{
    "data": {
        "actors": [
            {
                "full_name": "Demi\u00e1n Bichir",
                "gender": "m",
                "id": 118,
                "slug": "demian-bichir",
                "url": "https://www.filminlatino.mx/actor/demian-bichir"
            },
            {
                "full_name": "Jamie  Kierans",
                "gender": "m",
                "id": 5156,
                "slug": "jamie-kierans",
                "url": "https://www.filminlatino.mx/actor/jamie-kierans"
            },
            {
                "full_name": "Kerry  Condon",
                "gender": "f",
                "id": 4225,
                "slug": "kerry-condon",
                "url": "https://www.filminlatino.mx/actriz/kerry-condon"
            },
            {
                "full_name": "James  Cosmo",
                "gender": "m",
                "id": 4226,
                "slug": "james-cosmo",
                "url": "https://www.filminlatino.mx/actor/james-cosmo"
            },
            {
                "full_name": "Bruno Bichir",
                "gender": "m",
                "id": 803,
                "slug": "bruno-bichir",
                "url": "https://www.filminlatino.mx/actor/bruno-bichir"
            }
        ],
        "avg_votes": 8.8,
        "avg_votes_formatted": "8,8",
        "awards": [],
        "characters": [],
        "countries": [
            {
                "id": 102,
                "name": "Irlanda",
                "slug": "irlanda",
                "url": "https://www.filminlatino.mx/catalogo/pais/irlanda"
            },
            {
                "id": 134,
                "name": "Luxemburgo",
                "slug": "luxemburgo",
                "url": "https://www.filminlatino.mx/catalogo/pais/luxemburgo"
            }
        ],
        "directors": [
            {
                "full_name": "Ian  Power",
                "gender": "m",
                "id": 1475,
                "slug": "ian-power",
                "url": "https://www.filminlatino.mx/director/ian-power"
            }
        ],
        "duration_in_minutes": 94,
        "excerpt": "Un ni\u00f1o vive con la esperanza de volver a ver a su padre cuando un piloto aterriza de emergencia en su pueblo. Con el paso del tiempo, el visitante ser\u00e1 visto como figura paterna.",
        "external_links": [],
        "genres": [
            {
                "id": 3,
                "name": "Comedia",
                "slug": "comedia",
                "url": "https://www.filminlatino.mx/catalogo/genero/comedia"
            },
            {
                "id": 1,
                "name": "Drama",
                "slug": "drama",
                "url": "https://www.filminlatino.mx/catalogo/genero/drama"
            }
        ],
        "has_new_episodes": false,
        "id": 2797,
        "image_card": "https://static.filminlatino.mx/images/media/2797/4/card_0_3.jpg",
        "image_poster": "https://static.filminlatino.mx/images/media/2797/3/poster_0_3.jpg",
        "image_stills": [
            "https://static.filminlatino.mx/images/media/2797/6/still_1_3.jpg",
            "https://static.filminlatino.mx/images/media/2797/7/still_1_3.jpg",
            "https://static.filminlatino.mx/images/media/2797/4/still_5_3.jpg",
            "https://static.filminlatino.mx/images/media/2797/5/still_5_3.jpg",
            "https://static.filminlatino.mx/images/media/2797/13/still_6_3.jpg",
            "https://static.filminlatino.mx/images/media/2797/12/still_6_3.jpg",
            "https://static.filminlatino.mx/images/media/2797/10/still_7_3.jpg",
            "https://static.filminlatino.mx/images/media/2797/11/still_7_3.jpg",
            "https://static.filminlatino.mx/images/media/2797/4/still_8_3.jpg",
            "https://static.filminlatino.mx/images/media/2797/4/still_8_3.jpg",
            "https://static.filminlatino.mx/images/media/2797/9/still_9_3.jpg",
            "https://static.filminlatino.mx/images/media/2797/8/still_9_3.jpg"
        ],
        "is_serie_complete": false,
        "language": null,
        "num_votes": 29,
        "original_title": "The Runway",
        "producers": [
            {
                "acronym": "",
                "id": 1359,
                "name": "Film V\u00e4st",
                "slug": "film-vast",
                "url": "https://www.filminlatino.mx/producer/film-vast"
            }
        ],
        "qualification": {
            "code": "TP",
            "description": "Todos los p\u00fablicos",
            "id": 1,
            "name": "A"
        },
        "quality": "HD",
        "seasons_count": null,
        "slug": "amigos-por-accidente",
        "synopsis": "Paco es un ni\u00f1o de 9 a\u00f1os que vive en Dromoleen con su madre y a\u00f1ora\u00a0pasar tiempo con\u00a0su padre, as\u00ed que decide aprender espa\u00f1ol para cuando se reencuentre con \u00e9l. Una noche ocurre un accidente en el que\u00a0un piloto colombiano aterriza de emergencia en el pueblo. Nadie habla espa\u00f1ol en ese lugar con\u00a0excepci\u00f3n de Paco, quien se convertir\u00e1 en el traductor de su nueva figura paterna.",
        "tags": [
            {
                "id": 520,
                "name": "Padres en el cine",
                "slug": "padres-en-el-cine",
                "url": "https://www.filminlatino.mx/catalogo/tema/padres-en-el-cine"
            },
            {
                "id": 577,
                "name": "Relaci\u00f3n padre e hijo",
                "slug": "relacion-padre-e-hijo",
                "url": "https://www.filminlatino.mx/catalogo/tema/relacion-padre-e-hijo"
            },
            {
                "id": 19,
                "name": "Basada en hechos reales",
                "slug": "basada-en-hechos-reales",
                "url": "https://www.filminlatino.mx/catalogo/tema/basada-en-hechos-reales"
            },
            {
                "id": 873,
                "name": "Destinos",
                "slug": "destinos",
                "url": "https://www.filminlatino.mx/catalogo/tema/destinos"
            },
            {
                "id": 429,
                "name": "Multiculturalidad",
                "slug": "multiculturalidad",
                "url": "https://www.filminlatino.mx/catalogo/tema/multiculturalidad"
            },
            {
                "id": 677,
                "name": "Ni\u00f1os Protagonistas",
                "slug": "ninos-protagonistas",
                "url": "https://www.filminlatino.mx/catalogo/tema/ninos-protagonistas"
            },
            {
                "id": 276,
                "name": "Vida rural",
                "slug": "vida-rural",
                "url": "https://www.filminlatino.mx/catalogo/tema/vida-rural"
            },
            {
                "id": 210,
                "name": "FilminLatino Ni\u00f1os",
                "slug": "filminlatino-ninos",
                "url": "https://www.filminlatino.mx/catalogo/tema/filminlatino-ninos"
            },
            {
                "id": 174,
                "name": "Reencuentros",
                "slug": "reencuentros",
                "url": "https://www.filminlatino.mx/catalogo/tema/reencuentros"
            },
            {
                "id": 925,
                "name": "Enredos familiares",
                "slug": "enredos-familiares",
                "url": "https://www.filminlatino.mx/catalogo/tema/enredos-familiares"
            },
            {
                "id": 492,
                "name": "Suerte",
                "slug": "suerte",
                "url": "https://www.filminlatino.mx/catalogo/tema/suerte"
            },
            {
                "id": 990,
                "name": "Maleducados",
                "slug": "maleducados",
                "url": "https://www.filminlatino.mx/catalogo/tema/maleducados"
            },
            {
                "id": 1024,
                "name": "Amarok Films",
                "slug": "amarok-films",
                "url": "https://www.filminlatino.mx/catalogo/tema/amarok-films"
            },
            {
                "id": 839,
                "name": "9\u00b0 FICM",
                "slug": "90-ficm",
                "url": "https://www.filminlatino.mx/catalogo/tema/90-ficm"
            },
            {
                "id": 1138,
                "name": "Estrenos internacionales FICM",
                "slug": "estrenos-internacionales-ficm",
                "url": "https://www.filminlatino.mx/catalogo/tema/estrenos-internacionales-ficm"
            },
            {
                "id": 2218,
                "name": "M\u00e1s de los nominados al Ariel 63",
                "slug": "mas-de-los-nominados-al-ariel-63",
                "url": "https://www.filminlatino.mx/catalogo/tema/mas-de-los-nominados-al-ariel-63"
            },
            {
                "id": 2560,
                "name": "Ni\u00f1os y ni\u00f1as de la vida real",
                "slug": "ninos-y-ninas-de-la-vida-real",
                "url": "https://www.filminlatino.mx/catalogo/tema/ninos-y-ninas-de-la-vida-real"
            }
        ],
        "theater_income_formatted": null,
        "theater_release": null,
        "theater_release_date": null,
        "theater_spectators_formatted": null,
        "title": "Amigos por accidente",
        "type": "film",
        "url": "https://www.filminlatino.mx/pelicula/amigos-por-accidente",
        "versions": [
            {
                "codes": [],
                "id": 2678,
                "is_multi_audio": false,
                "language_audios": [
                    {
                        "is_original": false,
                        "iso_code": "or",
                        "name": "Original"
                    }
                ],
                "language_subtitles": [],
                "name": "Versi\u00f3n Original",
                "part": null,
                "type_id": 3
            }
        ],
        "video_background": null,
        "video_trailer": {
            "sources": [
                {
                    "codec": "h264",
                    "mime_type": "video/mp4",
                    "src": "https://trailermx.filmin.com/mx/extras/mp4/Runway.mp4"
                },
                {
                    "codec": "h264",
                    "mime_type": "application/vnd.apple.mpegurl",
                    "src": "https://trailermx.filmin.com/mx/extras/hls-h264/Runway/master.m3u8"
                },
                {
                    "codec": "hevc",
                    "mime_type": "application/vnd.apple.mpegurl",
                    "src": "https://trailermx.filmin.com/mx/extras/hls-h265/Runway/master.m3u8"
                }
            ]
        },
        "year": 2010
    }
}