{
    "data": {
        "actors": [
            {
                "full_name": "Jembie Almazan",
                "gender": "f",
                "id": 5741,
                "slug": "jembie-almazan",
                "url": "https://www.filminlatino.mx/actriz/jembie-almazan"
            },
            {
                "full_name": "Jonathan  Diaz Angulo",
                "gender": "f",
                "id": 5742,
                "slug": "jonathan-diaz-angulo",
                "url": "https://www.filminlatino.mx/actriz/jonathan-diaz-angulo"
            },
            {
                "full_name": "Bernardo Garnica Cruz",
                "gender": "m",
                "id": 5743,
                "slug": "bernardo-garnica-cruz",
                "url": "https://www.filminlatino.mx/actor/bernardo-garnica-cruz"
            }
        ],
        "avg_votes": 8.8,
        "avg_votes_formatted": "8,8",
        "awards": [
            {
                "category": "Selecci\u00f3n Oficial",
                "icon": "toronto-international-film-fest-canada",
                "name": "Toronto International Film Fest, Canad\u00e1 ",
                "slug": "toronto-international-film-fest-canada",
                "year": null
            },
            {
                "category": "Proyecci\u00f3n Especial",
                "icon": "toronto-international-film-fest-canada",
                "name": "Toronto International Film Fest, Canad\u00e1 ",
                "slug": "toronto-international-film-fest-canada",
                "year": null
            },
            {
                "category": "Selecci\u00f3n Oficial",
                "icon": "",
                "name": "Festival Internacional de Cine de Cartagena de Indias",
                "slug": "festival-internacional-de-cine-de-cartagena-de-indias",
                "year": null
            },
            {
                "category": "Selecci\u00f3n Oficial",
                "icon": "festival-internacional-de-cine-de-rotterdam",
                "name": "Festival Internacional de Cine de Rotterdam",
                "slug": "festival-internacional-de-cine-de-rotterdam",
                "year": null
            },
            {
                "category": "Nominaci\u00f3n Mejor Director",
                "icon": "festival-internacional-de-cine-de-rotterdam",
                "name": "Festival Internacional de Cine de Rotterdam",
                "slug": "festival-internacional-de-cine-de-rotterdam",
                "year": null
            },
            {
                "category": "Selecci\u00f3n Oficial",
                "icon": "festival-internacional-de-cine-de-donostia-san-sebastian-espana",
                "name": "Festival Internacional de Cine de Donostia \u0096 San Sebasti\u00e1n, Espa\u00f1a",
                "slug": "festival-internacional-de-cine-de-donostia-san-sebastian-espana",
                "year": null
            }
        ],
        "characters": [],
        "countries": [
            {
                "id": 38,
                "name": "Canad\u00e1",
                "slug": "canada",
                "url": "https://www.filminlatino.mx/catalogo/pais/canada"
            },
            {
                "id": 49,
                "name": "Colombia",
                "slug": "colombia",
                "url": "https://www.filminlatino.mx/catalogo/pais/colombia"
            },
            {
                "id": 157,
                "name": "M\u00e9xico",
                "slug": "mexico",
                "url": "https://www.filminlatino.mx/catalogo/pais/mexico"
            }
        ],
        "directors": [
            {
                "full_name": "Juan Andr\u00e9s Arango Garc\u00eda",
                "gender": "m",
                "id": 2192,
                "slug": "juan-andres-arango-garcia",
                "url": "https://www.filminlatino.mx/director/juan-andres-arango-garcia"
            }
        ],
        "duration_in_minutes": 108,
        "excerpt": "Pel\u00edcula que sigue tres historias de adolescentes que deben enfrentarse a la migraci\u00f3n y al cambio en sus\u00a0vidas.",
        "external_links": [],
        "genres": [
            {
                "id": 1,
                "name": "Drama",
                "slug": "drama",
                "url": "https://www.filminlatino.mx/catalogo/genero/drama"
            }
        ],
        "has_new_episodes": false,
        "id": 4907,
        "image_card": "https://static.filminlatino.mx/images/media/4907/2/card_0_3.jpg",
        "image_poster": "https://static.filminlatino.mx/images/media/4907/2/poster_0_3.jpg",
        "image_stills": [
            "https://static.filminlatino.mx/images/media/4907/3/still_1_3.jpg",
            "https://static.filminlatino.mx/images/media/4907/3/still_1_3.jpg",
            "https://static.filminlatino.mx/images/media/4907/2/still_2_3.jpg",
            "https://static.filminlatino.mx/images/media/4907/2/still_2_3.jpg",
            "https://static.filminlatino.mx/images/media/4907/3/still_3_3.jpg",
            "https://static.filminlatino.mx/images/media/4907/3/still_3_3.jpg",
            "https://static.filminlatino.mx/images/media/4907/2/still_4_3.jpg",
            "https://static.filminlatino.mx/images/media/4907/2/still_4_3.jpg",
            "https://static.filminlatino.mx/images/media/4907/2/still_5_3.jpg",
            "https://static.filminlatino.mx/images/media/4907/1/still_5_3.jpg",
            "https://static.filminlatino.mx/images/media/4907/2/still_6_3.jpg",
            "https://static.filminlatino.mx/images/media/4907/2/still_6_3.jpg",
            "https://static.filminlatino.mx/images/media/4907/2/still_7_3.jpg",
            "https://static.filminlatino.mx/images/media/4907/3/still_7_3.jpg",
            "https://static.filminlatino.mx/images/media/4907/2/still_8_3.jpg",
            "https://static.filminlatino.mx/images/media/4907/2/still_8_3.jpg",
            "https://static.filminlatino.mx/images/media/4907/2/still_9_3.jpg",
            "https://static.filminlatino.mx/images/media/4907/2/still_9_3.jpg"
        ],
        "is_serie_complete": false,
        "language": null,
        "num_votes": 28,
        "original_title": "X500",
        "producers": [],
        "qualification": {
            "code": "15+",
            "description": "Mayores de 15 a\u00f1os",
            "id": 3,
            "name": "B15"
        },
        "quality": "HD",
        "seasons_count": null,
        "slug": "x500",
        "synopsis": "Tres j\u00f3venes migrantes del continente americano se enfrentan a la p\u00e9rdida de un ser querido. A pesar de sus estilos de vida radicalmente diferentes y los miles de kil\u00f3metros que los separan, sus historias cobran eco en b\u00fasqueda de su propia identidad.<br>",
        "tags": [
            {
                "id": 1346,
                "name": "Drama",
                "slug": "drama",
                "url": "https://www.filminlatino.mx/catalogo/tema/drama"
            },
            {
                "id": 600,
                "name": "Drama MX",
                "slug": "drama-mx",
                "url": "https://www.filminlatino.mx/catalogo/tema/drama-mx"
            },
            {
                "id": 46,
                "name": "Historias cruzadas",
                "slug": "historias-cruzadas",
                "url": "https://www.filminlatino.mx/catalogo/tema/historias-cruzadas"
            },
            {
                "id": 1144,
                "name": "Vidas cruzadas",
                "slug": "vidas-cruzadas",
                "url": "https://www.filminlatino.mx/catalogo/tema/vidas-cruzadas"
            },
            {
                "id": 43,
                "name": "Migraci\u00f3n",
                "slug": "migracion",
                "url": "https://www.filminlatino.mx/catalogo/tema/migracion"
            },
            {
                "id": 480,
                "name": "Inmigraci\u00f3n",
                "slug": "inmigracion",
                "url": "https://www.filminlatino.mx/catalogo/tema/inmigracion"
            },
            {
                "id": 660,
                "name": "Cambio de vida",
                "slug": "cambio-de-vida",
                "url": "https://www.filminlatino.mx/catalogo/tema/cambio-de-vida"
            },
            {
                "id": 444,
                "name": "M\u00e9xico",
                "slug": "mexico",
                "url": "https://www.filminlatino.mx/catalogo/tema/mexico"
            },
            {
                "id": 289,
                "name": "Ciudad de M\u00e9xico",
                "slug": "ciudad-de-mexico",
                "url": "https://www.filminlatino.mx/catalogo/tema/ciudad-de-mexico"
            },
            {
                "id": 499,
                "name": "Pueblo",
                "slug": "pueblo",
                "url": "https://www.filminlatino.mx/catalogo/tema/pueblo"
            },
            {
                "id": 366,
                "name": "Culturas ind\u00edgenas",
                "slug": "culturas-indigenas",
                "url": "https://www.filminlatino.mx/catalogo/tema/culturas-indigenas"
            },
            {
                "id": 577,
                "name": "Relaci\u00f3n padre e hijo",
                "slug": "relacion-padre-e-hijo",
                "url": "https://www.filminlatino.mx/catalogo/tema/relacion-padre-e-hijo"
            },
            {
                "id": 378,
                "name": "Muerte",
                "slug": "muerte",
                "url": "https://www.filminlatino.mx/catalogo/tema/muerte"
            },
            {
                "id": 647,
                "name": "Vida en el campo",
                "slug": "vida-en-el-campo",
                "url": "https://www.filminlatino.mx/catalogo/tema/vida-en-el-campo"
            },
            {
                "id": 471,
                "name": "Mundo urbano",
                "slug": "mundo-urbano",
                "url": "https://www.filminlatino.mx/catalogo/tema/mundo-urbano"
            },
            {
                "id": 855,
                "name": "Realidad urbana",
                "slug": "realidad-urbana",
                "url": "https://www.filminlatino.mx/catalogo/tema/realidad-urbana"
            },
            {
                "id": 698,
                "name": "Abuelos",
                "slug": "abuelos",
                "url": "https://www.filminlatino.mx/catalogo/tema/abuelos"
            },
            {
                "id": 307,
                "name": "Campo",
                "slug": "campo",
                "url": "https://www.filminlatino.mx/catalogo/tema/campo"
            },
            {
                "id": 112,
                "name": "Racismo",
                "slug": "racismo",
                "url": "https://www.filminlatino.mx/catalogo/tema/racismo"
            },
            {
                "id": 284,
                "name": "Desigualdad social",
                "slug": "desigualdad-social",
                "url": "https://www.filminlatino.mx/catalogo/tema/desigualdad-social"
            },
            {
                "id": 137,
                "name": "Desigualdad laboral",
                "slug": "desigualdad-laboral",
                "url": "https://www.filminlatino.mx/catalogo/tema/desigualdad-laboral"
            },
            {
                "id": 318,
                "name": "Sue\u00f1o americano",
                "slug": "sueno-americano",
                "url": "https://www.filminlatino.mx/catalogo/tema/sueno-americano"
            },
            {
                "id": 341,
                "name": "Sue\u00f1os",
                "slug": "suenos",
                "url": "https://www.filminlatino.mx/catalogo/tema/suenos"
            },
            {
                "id": 255,
                "name": "Crimen y delincuencia",
                "slug": "crimen-y-delincuencia",
                "url": "https://www.filminlatino.mx/catalogo/tema/crimen-y-delincuencia"
            },
            {
                "id": 564,
                "name": "Vidas pasadas",
                "slug": "vidas-pasadas",
                "url": "https://www.filminlatino.mx/catalogo/tema/vidas-pasadas"
            },
            {
                "id": 474,
                "name": "Sobrevivir ",
                "slug": "sobrevivir",
                "url": "https://www.filminlatino.mx/catalogo/tema/sobrevivir"
            },
            {
                "id": 88,
                "name": "Viajes en el extranjero",
                "slug": "viajes-en-el-extranjero",
                "url": "https://www.filminlatino.mx/catalogo/tema/viajes-en-el-extranjero"
            },
            {
                "id": 1288,
                "name": "Viaje",
                "slug": "viaje",
                "url": "https://www.filminlatino.mx/catalogo/tema/viaje"
            },
            {
                "id": 1311,
                "name": "Comunidad",
                "slug": "comunidad",
                "url": "https://www.filminlatino.mx/catalogo/tema/comunidad"
            },
            {
                "id": 243,
                "name": "Infancia y adolescencia",
                "slug": "infancia-y-adolescencia",
                "url": "https://www.filminlatino.mx/catalogo/tema/infancia-y-adolescencia"
            },
            {
                "id": 6,
                "name": "Sobre la adolescencia",
                "slug": "sobre-la-adolescencia",
                "url": "https://www.filminlatino.mx/catalogo/tema/sobre-la-adolescencia"
            },
            {
                "id": 663,
                "name": "Vida cotidiana",
                "slug": "vida-cotidiana",
                "url": "https://www.filminlatino.mx/catalogo/tema/vida-cotidiana"
            },
            {
                "id": 873,
                "name": "Destinos",
                "slug": "destinos",
                "url": "https://www.filminlatino.mx/catalogo/tema/destinos"
            },
            {
                "id": 584,
                "name": "Derechos Humanos",
                "slug": "derechos-humanos",
                "url": "https://www.filminlatino.mx/catalogo/tema/derechos-humanos"
            },
            {
                "id": 316,
                "name": "Frontera",
                "slug": "frontera",
                "url": "https://www.filminlatino.mx/catalogo/tema/frontera"
            },
            {
                "id": 805,
                "name": "Refugiados",
                "slug": "refugiados",
                "url": "https://www.filminlatino.mx/catalogo/tema/refugiados"
            },
            {
                "id": 340,
                "name": "Juventud",
                "slug": "juventud",
                "url": "https://www.filminlatino.mx/catalogo/tema/juventud"
            },
            {
                "id": 1023,
                "name": "Alfhaville",
                "slug": "alfhaville",
                "url": "https://www.filminlatino.mx/catalogo/tema/alfhaville"
            },
            {
                "id": 1259,
                "name": "A\u00f1os 2010",
                "slug": "anos-2010",
                "url": "https://www.filminlatino.mx/catalogo/tema/anos-2010"
            },
            {
                "id": 1400,
                "name": "Arterias de la ciudad",
                "slug": "arterias-de-la-ciudad",
                "url": "https://www.filminlatino.mx/catalogo/tema/arterias-de-la-ciudad"
            },
            {
                "id": 1421,
                "name": "Sonidos del barrio",
                "slug": "sonidos-del-barrio",
                "url": "https://www.filminlatino.mx/catalogo/tema/sonidos-del-barrio"
            },
            {
                "id": 1452,
                "name": "Personajes que inspiran",
                "slug": "personajes-que-inspiran",
                "url": "https://www.filminlatino.mx/catalogo/tema/personajes-que-inspiran"
            },
            {
                "id": 1870,
                "name": "Un Festival Mexicano Los Cabos FF | FICG 35",
                "slug": "un-festival-mexicano-los-cabos-ff-ficg-35",
                "url": "https://www.filminlatino.mx/catalogo/tema/un-festival-mexicano-los-cabos-ff-ficg-35"
            },
            {
                "id": 1859,
                "name": "FICG 35",
                "slug": "ficg-35",
                "url": "https://www.filminlatino.mx/catalogo/tema/ficg-35"
            },
            {
                "id": 1969,
                "name": "2\u00b0 Muestra de Cine en Lenguas Ind\u00edgenas",
                "slug": "20-muestra-de-cine-en-lenguas-indigenas",
                "url": "https://www.filminlatino.mx/catalogo/tema/20-muestra-de-cine-en-lenguas-indigenas"
            },
            {
                "id": 1970,
                "name": "Miradas a grandes historias | 2\u00b0 Muestra de Cine en Lenguas Ind\u00edgenas",
                "slug": "miradas-a-grandes-historias-20-muestra-de-cine-en-lenguas-indigenas",
                "url": "https://www.filminlatino.mx/catalogo/tema/miradas-a-grandes-historias-20-muestra-de-cine-en-lenguas-indigenas"
            },
            {
                "id": 2546,
                "name": "Amor y muerte",
                "slug": "amor-y-muerte",
                "url": "https://www.filminlatino.mx/catalogo/tema/amor-y-muerte"
            },
            {
                "id": 1414,
                "name": "Recomendadas",
                "slug": "recomendadas",
                "url": "https://www.filminlatino.mx/catalogo/tema/recomendadas"
            },
            {
                "id": 2492,
                "name": "Viajes transformadores",
                "slug": "viajes-transformadores",
                "url": "https://www.filminlatino.mx/catalogo/tema/viajes-transformadores"
            },
            {
                "id": 2239,
                "name": "Afrodescendencias",
                "slug": "afrodescendencias",
                "url": "https://www.filminlatino.mx/catalogo/tema/afrodescendencias"
            },
            {
                "id": 2179,
                "name": "Cine mexicano contempor\u00e1neo",
                "slug": "cine-mexicano-contemporaneo",
                "url": "https://www.filminlatino.mx/catalogo/tema/cine-mexicano-contemporaneo"
            },
            {
                "id": 2718,
                "name": "M\u00e9xico y el mundo",
                "slug": "mexico-y-el-mundo",
                "url": "https://www.filminlatino.mx/catalogo/tema/mexico-y-el-mundo"
            },
            {
                "id": 2489,
                "name": "P\u00e9rdidas y duelos",
                "slug": "perdidas-y-duelos",
                "url": "https://www.filminlatino.mx/catalogo/tema/perdidas-y-duelos"
            },
            {
                "id": 2537,
                "name": "Memorias de la segregaci\u00f3n",
                "slug": "memorias-de-la-segregacion",
                "url": "https://www.filminlatino.mx/catalogo/tema/memorias-de-la-segregacion"
            },
            {
                "id": 2544,
                "name": "No ficci\u00f3n y docudrama",
                "slug": "no-ficcion-y-docudrama",
                "url": "https://www.filminlatino.mx/catalogo/tema/no-ficcion-y-docudrama"
            }
        ],
        "theater_income_formatted": null,
        "theater_release": 1563580800,
        "theater_release_date": 1563580800,
        "theater_spectators_formatted": null,
        "title": "X500",
        "type": "film",
        "url": "https://www.filminlatino.mx/pelicula/x500",
        "versions": [
            {
                "codes": [],
                "id": 4303,
                "is_multi_audio": false,
                "language_audios": [
                    {
                        "is_original": false,
                        "iso_code": "or",
                        "name": "Original"
                    }
                ],
                "language_subtitles": [],
                "name": "Versi\u00f3n Original con Subt\u00edtulos en Espa\u00f1ol",
                "part": null,
                "type_id": 1
            }
        ],
        "video_background": null,
        "video_trailer": {
            "sources": [
                {
                    "codec": "h264",
                    "mime_type": "video/mp4",
                    "src": "https://trailermx.filmin.com/mx/extras/mp4/X500.mp4"
                },
                {
                    "codec": "h264",
                    "mime_type": "application/vnd.apple.mpegurl",
                    "src": "https://trailermx.filmin.com/mx/extras/hls-h264/X500/master.m3u8"
                },
                {
                    "codec": "hevc",
                    "mime_type": "application/vnd.apple.mpegurl",
                    "src": "https://trailermx.filmin.com/mx/extras/hls-h265/X500/master.m3u8"
                }
            ]
        },
        "year": 2016
    }
}