{
    "data": {
        "actors": [
            {
                "full_name": "Nin\u00f3n del Castillo",
                "gender": "f",
                "id": 4100,
                "slug": "ninon-del-castillo",
                "url": "https://www.filminlatino.mx/actriz/ninon-del-castillo"
            },
            {
                "full_name": "Pascual Loayza",
                "gender": "m",
                "id": 4101,
                "slug": "pascual-loayza",
                "url": "https://www.filminlatino.mx/actor/pascual-loayza"
            }
        ],
        "avg_votes": 8.1,
        "avg_votes_formatted": "8,1",
        "awards": [
            {
                "category": "Participante Teddy ",
                "icon": "premio-teddy",
                "name": "Premio Teddy    ",
                "slug": "premio-teddy",
                "year": null
            },
            {
                "category": "Mejor Direcci\u00f3n ",
                "icon": "",
                "name": " Festival de Sundance",
                "slug": "festival-de-sundance",
                "year": 2009
            }
        ],
        "characters": [],
        "countries": [
            {
                "id": 29,
                "name": "Bolivia",
                "slug": "bolivia",
                "url": "https://www.filminlatino.mx/catalogo/pais/bolivia"
            }
        ],
        "directors": [
            {
                "full_name": "Juan Carlos  Valdivia",
                "gender": "m",
                "id": 1417,
                "slug": "juan-carlos-valdivia",
                "url": "https://www.filminlatino.mx/director/juan-carlos-valdivia"
            }
        ],
        "duration_in_minutes": 108,
        "excerpt": "Narra los \u00faltimos d\u00edas de una familia de clase alta, en un momento en el que el pa\u00eds ha elegido llevar a cabo grandes cambios sociales.",
        "external_links": [],
        "genres": [
            {
                "id": 1,
                "name": "Drama",
                "slug": "drama",
                "url": "https://www.filminlatino.mx/catalogo/genero/drama"
            }
        ],
        "has_new_episodes": false,
        "id": 2710,
        "image_card": "https://static.filminlatino.mx/images/media/2710/2/card_0_3.jpg",
        "image_poster": "https://static.filminlatino.mx/images/media/2710/2/poster_0_3.jpg",
        "image_stills": [
            "https://static.filminlatino.mx/images/media/2710/2/still_1_3.jpg",
            "https://static.filminlatino.mx/images/media/2710/2/still_1_3.jpg"
        ],
        "is_serie_complete": false,
        "language": null,
        "num_votes": 19,
        "original_title": "Zona sur",
        "producers": [
            {
                "acronym": "",
                "id": 1615,
                "name": "Cinen\u00f3mada",
                "slug": "cinenomada",
                "url": "https://www.filminlatino.mx/producer/cinenomada"
            }
        ],
        "qualification": {
            "code": "12+",
            "description": "Adolescentes de 12 a\u00f1os en adelante",
            "id": 2,
            "name": "B"
        },
        "quality": "HD",
        "seasons_count": null,
        "slug": "zona-sur",
        "synopsis": "La historia narra los \u00faltimos d\u00edas de una familia de clase alta, en un momento en el que el pa\u00eds ha elegido llevar a cabo grandes cambios sociales. Seleccionada por Bolivia como candidata al Oscar 2010 en la categor\u00eda de pel\u00edcula de habla no inglesa.",
        "tags": [
            {
                "id": 660,
                "name": "Cambio de vida",
                "slug": "cambio-de-vida",
                "url": "https://www.filminlatino.mx/catalogo/tema/cambio-de-vida"
            },
            {
                "id": 247,
                "name": "Relaciones familiares",
                "slug": "relaciones-familiares",
                "url": "https://www.filminlatino.mx/catalogo/tema/relaciones-familiares"
            },
            {
                "id": 252,
                "name": "Burgues\u00eda",
                "slug": "burguesia",
                "url": "https://www.filminlatino.mx/catalogo/tema/burguesia"
            },
            {
                "id": 51,
                "name": "Lucha de clases",
                "slug": "lucha-de-clases",
                "url": "https://www.filminlatino.mx/catalogo/tema/lucha-de-clases"
            },
            {
                "id": 394,
                "name": "Cine latinoamericano",
                "slug": "cine-latinoamericano",
                "url": "https://www.filminlatino.mx/catalogo/tema/cine-latinoamericano"
            },
            {
                "id": 825,
                "name": "En terapia",
                "slug": "en-terapia",
                "url": "https://www.filminlatino.mx/catalogo/tema/en-terapia"
            },
            {
                "id": 878,
                "name": "Madres inolvidables",
                "slug": "madres-inolvidables",
                "url": "https://www.filminlatino.mx/catalogo/tema/madres-inolvidables"
            },
            {
                "id": 1053,
                "name": "Cinenomada",
                "slug": "cinenomada",
                "url": "https://www.filminlatino.mx/catalogo/tema/cinenomada"
            },
            {
                "id": 937,
                "name": "Iberoam\u00e9rica ",
                "slug": "iberoamerica",
                "url": "https://www.filminlatino.mx/catalogo/tema/iberoamerica"
            },
            {
                "id": 2651,
                "name": "Filmes internacionales",
                "slug": "filmes-internacionales",
                "url": "https://www.filminlatino.mx/catalogo/tema/filmes-internacionales"
            }
        ],
        "theater_income_formatted": null,
        "theater_release": null,
        "theater_release_date": null,
        "theater_spectators_formatted": null,
        "title": "Zona sur",
        "type": "film",
        "url": "https://www.filminlatino.mx/pelicula/zona-sur",
        "versions": [
            {
                "codes": [],
                "id": 2070,
                "is_multi_audio": false,
                "language_audios": [
                    {
                        "is_original": false,
                        "iso_code": "or",
                        "name": "Original"
                    }
                ],
                "language_subtitles": [],
                "name": "Versi\u00f3n Original",
                "part": null,
                "type_id": 3
            }
        ],
        "video_background": null,
        "video_trailer": {
            "sources": [
                {
                    "codec": "h264",
                    "mime_type": "video/mp4",
                    "src": "https://trailermx.filmin.com/mx/extras/mp4/zona-sur.mp4"
                },
                {
                    "codec": "h264",
                    "mime_type": "application/vnd.apple.mpegurl",
                    "src": "https://trailermx.filmin.com/mx/extras/hls-h264/zona-sur/master.m3u8"
                },
                {
                    "codec": "hevc",
                    "mime_type": "application/vnd.apple.mpegurl",
                    "src": "https://trailermx.filmin.com/mx/extras/hls-h265/zona-sur/master.m3u8"
                }
            ]
        },
        "year": 2009
    }
}